dendrol
