Metadata-Version: 2.1
Name: dendrol
Version: 0.0.4
Summary: The STIX2 Pattern expression library for humans
Home-page: https://github.com/usePF/dendrol
Author: Perch Security
Author-email: hello@perchsecurity.com
Maintainer: Zach "theY4Kman" Kanzler
Maintainer-email: z@perchsecurity.com
License: MIT
Platform: UNKNOWN
Classifier: Development Status :: 3 - Alpha
Classifier: License :: OSI Approved :: MIT License
Classifier: Programming Language :: Python :: 3 :: Only
Classifier: Programming Language :: Python :: 3.6
Classifier: Programming Language :: Python :: 3.7
Classifier: Topic :: Security
Provides-Extra: dev
Provides-Extra: test
